LICENSE
MANIFEST.in
README.rst
requirements.txt
setup.cfg
setup.py
test-requirements.txt
steel_pigs/__init__.py
steel_pigs/pigs_config.py
steel_pigs/webapp.py
steel_pigs.egg-info/PKG-INFO
steel_pigs.egg-info/SOURCES.txt
steel_pigs.egg-info/dependency_links.txt
steel_pigs.egg-info/not-zip-safe
steel_pigs.egg-info/requires.txt
steel_pigs.egg-info/top_level.txt
steel_pigs/exceptions/__init__.py
steel_pigs/exceptions/pigs_exceptions.py
steel_pigs/pigs_app_settings/__init__.py
steel_pigs/pigs_app_settings/forms.py
steel_pigs/pigs_app_settings/frontend.py
steel_pigs/pigs_app_settings/nav.py
steel_pigs/plugins/__init__.py
steel_pigs/plugins/providers/__init__.py
steel_pigs/plugins/providers/formatterbase.py
steel_pigs/plugins/providers/ipxebase.py
steel_pigs/plugins/providers/noformat.py
steel_pigs/plugins/providers/pluginbase.py
steel_pigs/plugins/providers/provisionosbase.py
steel_pigs/plugins/providers/rpc_os_provision.py
steel_pigs/plugins/providers/sql.py
steel_pigs/plugins/providers/static_pxe_provider.py
steel_pigs/plugins/providers/static_version.py
steel_pigs/plugins/providers/versionbase.py
steel_pigs/templates/base.html
steel_pigs/templates/hardware.ipxe
steel_pigs/templates/home_form.html
steel_pigs/templates/pigs.ipxe
steel_pigs/templates/rpc-pre-seed.j2
steel_pigs/templates/rpc_default_lvm.j2
steel_pigs/templates/rpc_default_mirror.j2
steel_pigs/templates/rpc_default_network.j2
steel_pigs/templates/rpc_default_packages.j2
steel_pigs/templates/rpc_default_post_install.j2
steel_pigs/templates/rpc_default_users.j2