Metadata-Version: 1.0
Name: steel-pigs
Version: 0.4
Summary: Powerful iPXE Generation Service
Home-page: https://github.com/virtdevninja/steel_pigs
Author: Michael Rice
Author-email: michael@michaelrice.org
License: License :: OSI Approved :: Apache Software License
Platform: Windows
Platform: Linux
Platform: Solaris
Platform: Mac OS-X
Platform: Unix
